{
  "teamOverrides": {
"514": {"shortname": "Вторая СПб Гимназия #1: Cyber alliance"},
"309": {"shortname": "Гатчинский лицей №3: Alpha"},
"430": {"shortname": "ПФМЛ 239: программист, математик и прагматик"},
"210": {"shortname": "ГФМЛ 30: Галлий, уран, сера - цинк"},
"424": {"shortname": "Школа 1: Питуньи"},
"505": {"shortname": "`Санкт-Петербургский Пансион воспитанниц МО РФ`: Дебют"},
"517": {"shortname": "ФТШ + ГФМЛ 30: Кружок рисования"},
"304": {"shortname": "ФТШ: ЗАО Клуб Любителей Пельменей «Шлёпа»"},
"413": {"shortname": "СПб КВК: Убойная сила"},
"310": {"shortname": "ФМЛ 239: CyXaPuKu"},
"504": {"shortname": "СУНЦ СПБГУ: СУНЦ Академическая гимназия СПБГУ"},
"403": {"shortname": "Вторая СПб Гимназия #2: Лыпока)"},
"305": {"shortname": "ЛНМО+Школа 358+Школа 321: Идемпотент"},
"509": {"shortname": "239, 533: PSI"},
"214": {"shortname": "ФТШ: Пакетик грибов"},
"516": {"shortname": "ФТШ, 239, Лицей №14: качки и очки"},
"408": {"shortname": "Лицей ФТШ: Error 418"},
"212": {"shortname": "533+239: мы обязательно придумаем название"},
"202": {"shortname": "ГФМЛ 30 #01: 10-1-11-13-S"},
"308": {"shortname": "ГФМЛ 30 #02: 11-45-D"},
"423": {"shortname": "ГФМЛ 30 #03: 10-12-S"},
"502": {"shortname": "ГФМЛ 30 #04: 10-34-C"},
"431": {"shortname": "ГФМЛ 30 #05: 11-346-F"},
"201": {"shortname": "ГФМЛ 30 #06: 11-6-H"},
"411": {"shortname": "ГФМЛ 30 #07: 11-36-T"},
"216": {"shortname": "Президентский ФМЛ 239: 239-8 и Дмитрий"},
"410": {"shortname": "ЛНМО: Полупростор"},
"406": {"shortname": "ГФМЛ 30 #08: 8-34-L"},
"518": {"shortname": "ГФМЛ 30 #09: 8-123-R"},
"427": {"shortname": "ГФМЛ 30 #10: 9-2-D"},
"206": {"shortname": "ГФМЛ 30 #11: 9-13-E"},
"404": {"shortname": "ГФМЛ 30 #12: 9-14-V"},
"433": {"shortname": "ГФМЛ 30 #13: 9-23-P"},
"422": {"shortname": "ГФМЛ 30 #14: 9-24-N"},
"207": {"shortname": "ГФМЛ 30 #15: 9-35-S"},
"421": {"shortname": "ГФМЛ 30 #16: 9-124-K"},
"515": {"shortname": "ГФМЛ 30 #17: 9-134-Z"},
"415": {"shortname": "ЮМШ #533: ЗИК"},
"429": {"shortname": "ГФМЛ 30 #18: 10-1-M"},
"513": {"shortname": "ГФМЛ 30 #19: 10-5-T"},
"303": {"shortname": "ГФМЛ 30 #20: 10-56-B"},
"402": {"shortname": "ФТШ: Крокодилы"},
"215": {"shortname": "ГФМЛ 30 #21: 8-1-S"},
"435": {"shortname": "ГФМЛ 30: Таинственное мудрое дерево"},
"211": {"shortname": "ЮМШ #3: ITcommandочка"},
"418": {"shortname": "ФМЛ 239: Учхицми"},
"519": {"shortname": "ЮМШ #4: o5A"},
"507": {"shortname": "384+ФМЛ 366+393: Да."},
"203": {"shortname": "ЮМШ #6: Hello, world!"},
"432": {"shortname": "ФМЛ 239: Эден"},
"506": {"shortname": "ЮМШ #8: Казино Шрёдингера"},
"307": {"shortname": "ЮМШ: КБОА"},
"302": {"shortname": "ФТШ+617: Джиниус Кодерс"},
"417": {"shortname": "ГФМЛ 30: Больше нет вариантов"},
"512": {"shortname": "ЦПМ+9 Сосновый Бор: ..."},
"205": {"shortname": "ФТШ: Лютые Кабачки2007"},
"419": {"shortname": "Лицей 369: LastTask"},
"434": {"shortname": "ФМЛ 239: Помноженные на ноль"},
"511": {"shortname": "ГФМЛ 30: Мини-генераторы"},
"416": {"shortname": "ПФМЛ 239: Доктор Ливси"},
"414": {"shortname": "ПФМЛ №239 #228: ..."},
"501": {"shortname": "ГФМЛ 30: Тетрагидро..."},
"409": {"shortname": "ЛНМО: Абеленизация алгебры анонимных А."},
"426": {"shortname": "ГФМЛ 30 #22: 9-12-11-6-M"},
"508": {"shortname": "Лицей 64 + ФМЛ 239 + ФМЛ 30: тяжело..."},
"412": {"shortname": "ОЦ80 + 533 #1: "},
"407": {"shortname": "ЦОДИВ+80+Взмах: Всероснутые"},
"436": {"shortname": "ФМЛ 239: Уравнение Теплового Баланса"},
"204": {"shortname": "Лицей 144: 12 в квадрате"},
"405": {"shortname": "АГ им Д.К.Фаддеева: Эксперты в своем деле"},
"213": {"shortname": "ФМЛ 239 + Летово: Кватернионы"},
"420": {"shortname": "205 гимназия + ФТШ: йцукен"},
"428": {"shortname": "ФМЛ 239 + ЮМШ: Три Дырявых Ведра"},
"425": {"shortname": "Школа 1 + школа 173 + ФМЛ 366: ФКДО"},
"208": {"shortname": "ПФМЛ 239: ФМК"},
"401": {"shortname": "ЮМШ #7: мынеможемопределиться"},
"503": {"shortname": "ЮМШ+141 #5: ДиП"},
"301": {"shortname": "ЮМШ #777: fallsistem"},
"209": {"shortname": "ФМЛ239+ФТШ: Борис Инбос"},
"306": {"shortname": "ПФМЛ №239 + ФМЛ №366: Триплет"},
"510": {"shortname": "ПФМЛ 239: 239 forever"},
"520": {"shortname": "Гимназия 261 + СЗИУ РАНХиГС ФСПО: ARTELX"},
"524": {"shortname": "Гимназия 261: spb"},
"522": {"shortname": "Гимназия 261: Факториал"},
"523": {"shortname": "Лицей №64: Трес Амигос"},
"521": {"shortname": "ПФМЛ 239: Дикие пельмешки"},
"217": {"shortname": "Гимназия 261: легенда"}
},
  "problemOverrides": {
    "A":{"color":"#129C62"},
    "B":{"color":"#010101"},
    "C":{"color":"#958F29"},
    "D":{"color":"#86969B"},
    "E":{"color":"#E878A6"},
    "F":{"color":"#8E8C8F"},
    "G":{"color":"#BEB772"},
    "H":{"color":"#D560B1"},
    "I":{"color":"#E63954"},
    "J":{"color":"#8D669C"},
    "K":{"color":"#B47B36"},
    "L":{"color":"#AAB6A8"},
    "M":{"color":"#b27a36"},
    "N":{"color":"#b8a986"},
    "O":{"color":"#964161"},
    "W":{"color":"#e6194B"},
    "X":{"color":"#3cb44b"},
    "Y":{"color":"#ffe119"},
    "Z":{"color":"#4363d8"}
  }
 }