{"id":119,"university":{"fullName":"University of Tehran","shortName":"UT","region":"Asia","hashTag":"UTehran","url":"http://www.fos.ut.ac.ir","myIcpcId":"313617","appearances":4,"wins":0,"gold":0,"silver":0,"bronze":0,"regionalChampionships":0},"team":{"name":"NeshesTeam","regionals":["The 2016 ACM-ICPC Asia Tehran Regional Contest, 2nd","Asia Tehran - Internet Programming Contest, 3rd"],"openCupPlace":-1,"openCupTimes":0},"coach":{"name":"Amirhossein Shapori","altNames":["Shapori Amirhossein","Amirhossein Shapoori","Shapoori Amirhossein"],"tcHandle":"shamir14","tcId":"23041840","tcRating":1714,"cfHandle":"shamir0xe","cfRating":1912,"twitterHandle":"shamir0xe","achievements":[{"achievement":"ACM ICPC Finalist (2016)","priority":1001},{"achievement":"Bayan Finalist (2015)","priority":26}]},"contestants":[{"name":"Shayan Hosseini","altNames":["Hosseini Shayan","Shayan Hosseiny","Hosseiny Shayan"],"tcRating":-1,"cfHandle":"ShayanH","cfRating":2085,"twitterHandle":"seshayanh","achievements":[]},{"name":"Abtin Bateni","altNames":["Bateni Abtin","abtin bateni","bateni abtin"],"tcRating":-1,"cfHandle":"mrTux","cfRating":1989,"twitterHandle":"AbtinBateni","achievements":[]},{"name":"Navid RahimiDanesh","altNames":["RahimiDanesh Navid","Navid Rahimi Danesh","Rahimi Danesh Navid"],"tcRating":-1,"cfHandle":"navidda","cfRating":2053,"achievements":[]}]}