{
    "teamOverrides": {
        "142569": {
            "shortname": "Грошев Владимир, 6"
        },
        "142570": {
            "shortname": "Филатов Артем, 6"
        },
        "142571": {
            "shortname": "Сидоров Иван, 6"
        },
        "142572": {
            "shortname": "Бродецкий Владислав, 6"
        },
        "142573": {
            "shortname": "Ларионов Елисей, 6"
        },
        "142574": {
            "shortname": "Казарновский Михаил, 6"
        },
        "142575": {
            "shortname": "Щекин Сергей, 6"
        },
        "142576": {
            "shortname": "Дудоладов Андрей, 6"
        },
        "142577": {
            "shortname": "Мягков Артём, 6"
        },
        "142578": {
            "shortname": "Трусов Иван, 6"
        },
        "142579": {
            "shortname": "Гагарин Герман, 4"
        },
        "142580": {
            "shortname": "Сосенушкин Мстислав, 6"
        },
        "142581": {
            "shortname": "Калинин Николай, 6"
        },
        "142582": {
            "shortname": "Вербицкий Александр, 6"
        },
        "142583": {
            "shortname": "Гродская Алиса, 6"
        },
        "142584": {
            "shortname": "Клочков Дмитрий, 6"
        },
        "142585": {
            "shortname": "Анохин Борис, 6"
        },
        "142586": {
            "shortname": "Усов Илья, 6"
        },
        "142587": {
            "shortname": "Макаров Всеволод, 6"
        },
        "142588": {
            "shortname": "Жеглова Дарья, 6"
        },
        "142589": {
            "shortname": "Тютюнник Павел, 6"
        },
        "142590": {
            "shortname": "Салангин Влад, 5"
        },
        "142591": {
            "shortname": "Петров Даниил, 6"
        },
        "142592": {
            "shortname": "Мелешкин Иван, 6"
        },
        "142593": {
            "shortname": "Оленин Глеб, 5"
        },
        "142594": {
            "shortname": "Деревенский Дмитрий, 6"
        },
        "142595": {
            "shortname": "Пархоменко Анастасия, 6"
        },
        "142596": {
            "shortname": "Фенина Анастасия, 6"
        },
        "142597": {
            "shortname": "Конарев Валентин, 6"
        },
        "142598": {
            "shortname": "Шарлай Семен, 5"
        },
        "142599": {
            "shortname": "Лагашина Марина, 5"
        },
        "142600": {
            "shortname": "Скляренко Денис, 6"
        },
        "142601": {
            "shortname": "Бабин Илья, 6"
        },
        "142602": {
            "shortname": "Кудинов Фёдор, 6"
        },
        "142603": {
            "shortname": "Грицаев Николай, 6"
        },
        "142604": {
            "shortname": "Чашин Ярослав, 6"
        },
        "142605": {
            "shortname": "Протопопов Илья, 5"
        },
        "142606": {
            "shortname": "Быстров Игорь, 5"
        },
        "142607": {
            "shortname": "Чикалкин Иван, 5"
        },
        "142608": {
            "shortname": "Лекомцев Данил, 5"
        },
        "142609": {
            "shortname": "Белов Денис, 6"
        },
        "142610": {
            "shortname": "Постников Матвей, 6"
        },
        "142611": {
            "shortname": "Бессолов Андрей, 5"
        },
        "142612": {
            "shortname": "Харина Арина, 6"
        },
        "142613": {
            "shortname": "Хамитов Григорий, 5"
        },
        "142614": {
            "shortname": "Егоров Марк, 6"
        },
        "142615": {
            "shortname": "Павлючков Владислав, 5"
        },
        "142616": {
            "shortname": "Никитина Тала, 6"
        },
        "142617": {
            "shortname": "Тульская Дарья, 5"
        },
        "142618": {
            "shortname": "Хозина Алиса, 4"
        },
        "142619": {
            "shortname": "Меньщиков Егор, 5"
        },
        "142620": {
            "shortname": "Зонов Еремей, 6"
        },
        "142621": {
            "shortname": "Суздаленко Майя, 6"
        },
        "142622": {
            "shortname": "Смирнов Всеволод, 6"
        },
        "142623": {
            "shortname": "Красносельская Екатерина, 6"
        },
        "142624": {
            "shortname": "Майборода Степан, 6"
        },
        "142625": {
            "shortname": "Телюков Максим, 6"
        },
        "142626": {
            "shortname": "Башлак Даниил, 6"
        },
        "142627": {
            "shortname": "Дмитриенко Лада, 6"
        },
        "142628": {
            "shortname": "Семенов Роман, 6"
        },
        "142629": {
            "shortname": "Ходжаев Амир, 6"
        },
        "142630": {
            "shortname": "Носов Всеволод, 5"
        },
        "142631": {
            "shortname": "Половинкин Артём, 6"
        },
        "142632": {
            "shortname": "Хизгияев Лев, 6"
        },
        "142633": {
            "shortname": "Иноземцев Михаил, 6"
        },
        "142634": {
            "shortname": "Уелданов Данис, 5"
        },
        "142635": {
            "shortname": "Гладыш Андрей, 6"
        },
        "142636": {
            "shortname": "Собов Артём, 6"
        },
        "142637": {
            "shortname": "Хохлов Ярослав, 6"
        },
        "142638": {
            "shortname": "Федотова Виктория, 6"
        },
        "142639": {
            "shortname": "Киселев Матвей, 6"
        },
        "142640": {
            "shortname": "Плешкова Виктория, 4"
        },
        "142641": {
            "shortname": "КОЖЕВНИКОВ Илья, 6"
        },
        "142642": {
            "shortname": "Корнилов Артём, 6"
        },
        "142643": {
            "shortname": "Быкова Ксения, 6"
        },
        "142644": {
            "shortname": "Мелехин Даниил, 6"
        },
        "142645": {
            "shortname": "Лопаткин Егор, 6"
        },
        "142646": {
            "shortname": "Левинзон Лев, 6"
        },
        "142647": {
            "shortname": "Бурлак Леонид, 6"
        },
        "142648": {
            "shortname": "Гайсин Самат, 6"
        },
        "142649": {
            "shortname": "Липинский Дмитрий, 6"
        },
        "142650": {
            "shortname": "Ушаков Фёдор, 6"
        },
        "142651": {
            "shortname": "Самсонов Игорь, 6"
        },
        "142652": {
            "shortname": "Демченко Максим, 6"
        },
        "142653": {
            "shortname": "Зелёная Светлана, 6"
        },
        "142654": {
            "shortname": "Пронин Алексей, 6"
        },
        "142655": {
            "shortname": "Савостьянова Анжелика, 6"
        },
        "142656": {
            "shortname": "Куля Борис, 5"
        },
        "142657": {
            "shortname": "Калюжный Александр, 6"
        },
        "142658": {
            "shortname": "Сильченко Матвей, 6"
        },
        "142659": {
            "shortname": "Говзман Кирилл, 6"
        },
        "142660": {
            "shortname": "Голубцов Владимир, 6"
        },
        "142661": {
            "shortname": "Марченко Владислав, 5"
        },
        "142662": {
            "shortname": "Корчагина Алёна, 5"
        },
        "142663": {
            "shortname": "Баянов Андрей, 6"
        },
        "142664": {
            "shortname": "Шишкин Иван, 5"
        },
        "142665": {
            "shortname": "Мещеряков Савелий, 4"
        },
        "142666": {
            "shortname": "Кабалин Алексей, 6"
        },
        "142667": {
            "shortname": "Григорьев Алексей, 5"
        },
        "142668": {
            "shortname": "Андреева Маргарита, 6"
        },
        "142669": {
            "shortname": "Василевицкий Лев, 4"
        },
        "142670": {
            "shortname": "Романова Арина, 6"
        },
        "142671": {
            "shortname": "Степанов Даниил, 6"
        },
        "142672": {
            "shortname": "Филиппов Владислав, 6"
        },
        "142673": {
            "shortname": "Грибакин Иван, 6"
        },
        "142674": {
            "shortname": "Суриков Владислав, 4"
        },
        "142675": {
            "shortname": "Майоров Глеб, 5"
        },
        "142676": {
            "shortname": "Жуков Богдан, 6"
        },
        "142677": {
            "shortname": "Балкин Георгий, 6"
        },
        "142678": {
            "shortname": "Погадаев Александр, 6"
        },
        "142679": {
            "shortname": "Коротков Александр, 5"
        },
        "142680": {
            "shortname": "Трусов Михаил, 4"
        },
        "142681": {
            "shortname": "Бузинов Егор, 6"
        },
        "142682": {
            "shortname": "Адаменко Любомир, 5"
        },
        "142683": {
            "shortname": "Петков Александр, 6"
        },
        "142684": {
            "shortname": "Вяткин Егор, 6"
        },
        "142685": {
            "shortname": "Романов Иван, 5"
        },
        "142686": {
            "shortname": "Алексеенко Алина, 6"
        },
        "142687": {
            "shortname": "Денисов Максим, 6"
        },
        "142688": {
            "shortname": "Матюшкина Софья, 6"
        },
        "142689": {
            "shortname": "Лесных Арина, 6"
        },
        "142690": {
            "shortname": "Давыдов Пётр, 6"
        },
        "142691": {
            "shortname": "Сыцко Тимофей, 6"
        },
        "142692": {
            "shortname": "Цуканов Александр, 5"
        },
        "142693": {
            "shortname": "Старчак Илья, 6"
        },
        "142694": {
            "shortname": "Пинский Александр, 4"
        },
        "142695": {
            "shortname": "Овсянников Павел, 6"
        },
        "142696": {
            "shortname": "Нелипович Тимофей, 6"
        },
        "142697": {
            "shortname": "Акимова Вероника, 6"
        },
        "142698": {
            "shortname": "Акимов Виталий, 6"
        },
        "142699": {
            "shortname": "Акимова Виктория, 6"
        },
        "142700": {
            "shortname": "Соколов Матвей, 6"
        },
        "142701": {
            "shortname": "Гуртовой Александр, 6"
        },
        "142702": {
            "shortname": "Девяткина Капитолина, 6"
        },
        "142703": {
            "shortname": "Жуков Фёдор, 5"
        },
        "142704": {
            "shortname": "Алексеев Юрий, 5"
        },
        "142705": {
            "shortname": "Симакин Вадим, 6"
        },
        "142706": {
            "shortname": "Комендантов Марк, 4"
        },
        "142707": {
            "shortname": "Тупицын Родион, 6"
        },
        "142708": {
            "shortname": "Метляхина Ольга, 6"
        },
        "142709": {
            "shortname": "Парпиева Ольга, 6"
        },
        "142710": {
            "shortname": "mosolymp-2023-6142"
        },
        "142711": {
            "shortname": "mosolymp-2023-6143"
        },
        "142712": {
            "shortname": "mosolymp-2023-6144"
        },
        "142713": {
            "shortname": "mosolymp-2023-6145"
        },
        "142714": {
            "shortname": "mosolymp-2023-6146"
        },
        "142715": {
            "shortname": "mosolymp-2023-6147"
        },
        "142716": {
            "shortname": "mosolymp-2023-6148"
        },
        "142717": {
            "shortname": "mosolymp-2023-6149"
        },
        "142718": {
            "shortname": "mosolymp-2023-6150"
        },
        "142719": {
            "shortname": "mosolymp-2023-6151"
        },
        "142720": {
            "shortname": "mosolymp-2023-6152"
        },
        "142721": {
            "shortname": "mosolymp-2023-6153"
        },
        "142722": {
            "shortname": "mosolymp-2023-6154"
        },
        "142723": {
            "shortname": "mosolymp-2023-6155"
        },
        "142724": {
            "shortname": "mosolymp-2023-6156"
        },
        "142725": {
            "shortname": "mosolymp-2023-6157"
        },
        "142726": {
            "shortname": "mosolymp-2023-6158"
        },
        "142727": {
            "shortname": "mosolymp-2023-6159"
        },
        "142728": {
            "shortname": "mosolymp-2023-6160"
        },
        "142729": {
            "shortname": "mosolymp-2023-6161"
        },
        "142730": {
            "shortname": "mosolymp-2023-6162"
        },
        "142731": {
            "shortname": "mosolymp-2023-6163"
        },
        "142732": {
            "shortname": "mosolymp-2023-6164"
        },
        "142733": {
            "shortname": "mosolymp-2023-6165"
        },
        "142734": {
            "shortname": "mosolymp-2023-6166"
        },
        "142735": {
            "shortname": "mosolymp-2023-6167"
        },
        "142736": {
            "shortname": "mosolymp-2023-6168"
        },
        "142737": {
            "shortname": "mosolymp-2023-6169"
        },
        "142738": {
            "shortname": "mosolymp-2023-6170"
        },
        "142739": {
            "shortname": "mosolymp-2023-6171"
        },
        "142740": {
            "shortname": "mosolymp-2023-6172"
        },
        "142741": {
            "shortname": "mosolymp-2023-6173"
        },
        "142742": {
            "shortname": "mosolymp-2023-6174"
        },
        "142743": {
            "shortname": "mosolymp-2023-6175"
        },
        "142744": {
            "shortname": "mosolymp-2023-6176"
        },
        "142745": {
            "shortname": "mosolymp-2023-6177"
        },
        "142746": {
            "shortname": "mosolymp-2023-6178"
        },
        "142747": {
            "shortname": "mosolymp-2023-6179"
        },
        "142748": {
            "shortname": "mosolymp-2023-6180"
        },
        "142749": {
            "shortname": "mosolymp-2023-6181"
        },
        "142750": {
            "shortname": "mosolymp-2023-6182"
        },
        "142751": {
            "shortname": "mosolymp-2023-6183"
        },
        "142752": {
            "shortname": "mosolymp-2023-6184"
        },
        "142753": {
            "shortname": "mosolymp-2023-6185"
        },
        "142754": {
            "shortname": "mosolymp-2023-6186"
        },
        "142755": {
            "shortname": "mosolymp-2023-6187"
        },
        "142756": {
            "shortname": "mosolymp-2023-6188"
        },
        "142757": {
            "shortname": "mosolymp-2023-6189"
        },
        "142758": {
            "shortname": "mosolymp-2023-6190"
        },
        "142759": {
            "shortname": "mosolymp-2023-6191"
        },
        "142760": {
            "shortname": "mosolymp-2023-6192"
        },
        "142761": {
            "shortname": "mosolymp-2023-6193"
        },
        "142762": {
            "shortname": "mosolymp-2023-6194"
        },
        "142763": {
            "shortname": "mosolymp-2023-6195"
        },
        "142764": {
            "shortname": "mosolymp-2023-6196"
        },
        "142765": {
            "shortname": "mosolymp-2023-6197"
        },
        "142766": {
            "shortname": "mosolymp-2023-6198"
        },
        "142767": {
            "shortname": "mosolymp-2023-6199"
        },
        "142768": {
            "shortname": "mosolymp-2023-6200"
        }
    },
    "problemOverrides": {
        "A": {
            "color": "#e6194bff"
        },
        "B": {
            "color": "#3cb44bff"
        },
        "C": {
            "color": "#ffe119ff"
        },
        "D": {
            "color": "#4363d8ff"
        },
        "E": {
            "color": "#f58231ff"
        }
    },
    "scoreboardOverrides": {
        "showTeamsWithoutSubmissions": false
    },
    "startTime": "2023-02-12 10:30"
}